inline_files.py
inline_files-1.0.0.dist-info/LICENSE
inline_files-1.0.0.dist-info/WHEEL
inline_files-1.0.0.dist-info/METADATA
inline_files-1.0.0.dist-info/RECORD
