Metadata-Version: 2.1
Name: inline_files
Version: 1.0.0
Summary: Read inline files stored inside another file.
Keywords: files,inline,reader,parser
Author-email: Sofia Santos <sofiarsantos31@gmail.com>
Requires-Python: >=3.10
Classifier: License :: OSI Approved :: MIT License
Requires-Dist: pyyaml >= 6.0
Requires-Dist: pytest ; extra == "dev"
Provides-Extra: dev
